[{"name":"أحمد","number":1,"path":"الملك عبدالعزيز","section":"مركز 1","phone":500000001},{"name":"محمد","number":2,"path":"الملك فيصل","section":"مركز 2","phone":500000002},{"name":"علي","number":3,"path":"القصر","section":"مركز 3","phone":500000003},{"name":"يوسف","number":4,"path":"الملك عبدالعزيز","section":"مركز 1","phone":500000004},{"name":"عبدالله","number":5,"path":"الملك فيصل","section":"مركز 2","phone":500000005},{"name":"فاطمة","number":6,"path":"القصر","section":"مركز 3","phone":500000006},{"name":"خديجة","number":7,"path":"الملك عبدالعزيز","section":"مركز 1","phone":500000007},{"name":"زينب","number":8,"path":"الملك فيصل","section":"مركز 2","phone":500000008},{"name":"عائشة","number":9,"path":"القصر","section":"مركز 3","phone":500000009},{"name":"عمر","number":10,"path":"الملك عبدالعزيز","section":"مركز 1","phone":500000010}]